trello_watchman/__about__.py
trello_watchman/__init__.py
trello_watchman/__main__.py
trello_watchman/config.py
trello_watchman/logger.py
trello_watchman/trello_wrapper.py
trello_watchman/rules/files/archive_files.yaml
trello_watchman/rules/files/budget_files.yaml
trello_watchman/rules/files/cv_files.yaml
trello_watchman/rules/files/excel_docs.yaml
trello_watchman/rules/files/interesting_files.yaml
trello_watchman/rules/files/powerpoint_files.yaml
trello_watchman/rules/files/word_files.yaml
trello_watchman/rules/pii/bank_cards.yaml
trello_watchman/rules/pii/cusip_numbers.yaml
trello_watchman/rules/pii/date_of_birth.yaml
trello_watchman/rules/pii/drivers_licence_uk.yaml
trello_watchman/rules/pii/iban_numbers.yaml
trello_watchman/rules/pii/itin_numbers.yaml
trello_watchman/rules/pii/ni_numbers_uk.yaml
trello_watchman/rules/pii/passport_numbers.yaml
trello_watchman/rules/pii/passwords.yaml
trello_watchman/rules/pii/ssn_us.yaml
trello_watchman/rules/tokens/access_tokens.yaml
trello_watchman/rules/tokens/aws_tokens.yaml
trello_watchman/rules/tokens/azure_api_tokens.yaml
trello_watchman/rules/tokens/bearer_tokens.yaml
trello_watchman/rules/tokens/client_secrets.yaml
trello_watchman/rules/tokens/cloudflare_api_tokens.yaml
trello_watchman/rules/tokens/facebook_access_tokens.yaml
trello_watchman/rules/tokens/facebook_secret_tokens.yaml
trello_watchman/rules/tokens/github_api_tokens.yaml
trello_watchman/rules/tokens/google_api_tokens.yaml
trello_watchman/rules/tokens/heroku_tokens.yaml
trello_watchman/rules/tokens/mailchimp_api_tokens.yaml
trello_watchman/rules/tokens/mailgun_api_tokens.yaml
trello_watchman/rules/tokens/mastercard_datacash_tokens.yaml
trello_watchman/rules/tokens/misc_private_keys.yaml
trello_watchman/rules/tokens/ms_nuget_key.yaml
trello_watchman/rules/tokens/pagerduty_tokens.yaml
trello_watchman/rules/tokens/pgp_private_keys.yaml
trello_watchman/rules/tokens/private_tokens.yaml
trello_watchman/rules/tokens/shodan_api_tokens.yaml
trello_watchman-1.0.0.dist-info/LICENSE
trello_watchman-1.0.0.dist-info/METADATA
trello_watchman-1.0.0.dist-info/WHEEL
trello_watchman-1.0.0.dist-info/entry_points.txt
trello_watchman-1.0.0.dist-info/top_level.txt
trello_watchman-1.0.0.dist-info/RECORD
