Metadata-Version: 2.1
Name: trello-watchman
Version: 1.0.0
Summary: Monitoring your Trello boards for sensitive information
Home-page: https://github.com/PaperMtn/trello-watchman
Author: PaperMtn
Author-email: papermtn@protonmail.com
License: GPL-3.0
Keywords: audit trello trello-watchman watchman blue-team red-team threat-hunting
Platform: UNKNOWN
Classifier: Intended Audience :: Information Technology
Classifier: Topic :: Security
Classifier: License :: OSI Approved :: GNU General Public License v3 (GPLv3)
Classifier: Programming Language :: Python :: 3
Classifier: Programming Language :: Python :: 3.5
Classifier: Programming Language :: Python :: 3.6
Classifier: Programming Language :: Python :: 3.7
Classifier: Programming Language :: Python :: 3.8
Requires-Dist: requests
Requires-Dist: PyYAML
Requires-Dist: simplejson
